README.rst
setup.py
src/dogecoin_python.egg-info/PKG-INFO
src/dogecoin_python.egg-info/SOURCES.txt
src/dogecoin_python.egg-info/dependency_links.txt
src/dogecoin_python.egg-info/top_level.txt
src/dogecoinrpc/__init__.py
src/dogecoinrpc/config.py
src/dogecoinrpc/connection.py
src/dogecoinrpc/data.py
src/dogecoinrpc/exceptions.py
src/dogecoinrpc/proxy.py
src/dogecoinrpc/util.py