Metadata-Version: 1.1
Name: dogecoin-python
Version: 0.1.3
Summary: Friendly Dogecoin JSON-RPC API binding for Python
Home-page: https://github.com/jcsaaddupuy/dogecoin-python
Author: UNKNOWN
Author-email: UNKNOWN
License: UNKNOWN
Platform: UNKNOWN
Classifier: Development Status :: 4 - Beta
Classifier: Environment :: Console
Classifier: Environment :: Web Environment
Classifier: Intended Audience :: Developers
Classifier: Programming Language :: Python
Classifier: License :: OSI Approved :: MIT License
Classifier: Topic :: Office/Business :: Financial
